scripts/build_translations.py
scripts/compile_translations.py
skill_security_scan-1.0.0.dist-info/licenses/LICENSE
skills/test.md
src/__init__.py
src/__main__.py
src/cli.py
src/config_loader.py
src/rules_factory.py
src/i18n/__init__.py
src/reporters/__init__.py
src/reporters/console.py
src/reporters/html_report.py
src/reporters/json_report.py
src/rules/__init__.py
src/rules/base.py
src/rules/command.py
src/rules/dependencies.py
src/rules/fileops.py
src/rules/injection.py
src/rules/network.py
src/scanner/__init__.py
src/scanner/analyzer.py
src/scanner/detector.py
src/scanner/parser.py
skill_security_scan-1.0.0.dist-info/METADATA
skill_security_scan-1.0.0.dist-info/WHEEL
skill_security_scan-1.0.0.dist-info/entry_points.txt
skill_security_scan-1.0.0.dist-info/top_level.txt
skill_security_scan-1.0.0.dist-info/RECORD
