Metadata-Version: 2.4
Name: skill-security-scan
Version: 1.0.0
Summary: Claude Skills 安全扫描工具
Author-email: WellAlly Team <huifer97@163.com>
Maintainer-email: WellAlly Team <huifer97@163.com>
License: MIT
Project-URL: Homepage, https://www.wellally.tech/
Project-URL: Documentation, https://github.com/huifer/skill-security-scan/blob/main/docs/README.md
Project-URL: Repository, https://github.com/huifer/skill-security-scan
Project-URL: Issues, https://github.com/huifer/skill-security-scan/issues
Keywords: security,scanner,claude,skills,static-analysis,code-security
Classifier: Development Status :: 4 - Beta
Classifier: Intended Audience :: Developers
Classifier: Topic :: Security
Classifier: Topic :: Software Development :: Quality Assurance
Classifier: Topic :: Software Development :: Testing
Classifier: License :: OSI Approved :: MIT License
Classifier: Programming Language :: Python :: 3
Classifier: Programming Language :: Python :: 3.9
Classifier: Programming Language :: Python :: 3.10
Classifier: Programming Language :: Python :: 3.11
Classifier: Programming Language :: Python :: 3.12
Classifier: Operating System :: OS Independent
Classifier: Natural Language :: Chinese (Simplified)
Classifier: Natural Language :: English
Requires-Python: >=3.9
License-File: LICENSE
Requires-Dist: pyyaml>=6.0
Requires-Dist: click>=8.0.0
Provides-Extra: dev
Requires-Dist: pytest>=7.0.0; extra == "dev"
Requires-Dist: pytest-cov>=4.0.0; extra == "dev"
Requires-Dist: black>=23.0.0; extra == "dev"
Requires-Dist: ruff>=0.1.0; extra == "dev"
Requires-Dist: mypy>=1.0.0; extra == "dev"
Provides-Extra: docs
Requires-Dist: sphinx>=5.0.0; extra == "docs"
Requires-Dist: sphinx-rtd-theme>=1.0.0; extra == "docs"
Requires-Dist: myst-parser>=0.18.0; extra == "docs"
Provides-Extra: all
Requires-Dist: skill-security-scan[dev,docs]; extra == "all"
Dynamic: license-file
